gef_reader/__init__.py
gef_reader/gef_parser.py
gef_reader/utils/pytess_main.py
gef_reader/utils/pytess_tesselator.py_backup
gef_reader-0.1.1.dist-info/METADATA
gef_reader-0.1.1.dist-info/WHEEL
gef_reader-0.1.1.dist-info/licenses/LICENSE
gef_reader-0.1.1.dist-info/RECORD
