Metadata-Version: 2.4
Name: gef-reader
Version: 0.1.1
Summary: A simple pure-python implementation to parse .gef.txt files / CPT measurement data in ASCII format.
License-File: LICENSE
Requires-Python: >=3.12
